enka/__init__.py
enka/errors.py
enka/gi.py
enka/hsr.py
enka/utils.py
enka/assets/data.py
enka/assets/updater.py
enka/assets/gi/file_paths.py
enka/assets/gi/manager.py
enka/assets/hsr/file_paths.py
enka/assets/hsr/manager.py
enka/clients/__init__.py
enka/clients/base.py
enka/clients/cache.py
enka/clients/gi.py
enka/clients/hsr.py
enka/constants/gi.py
enka/constants/hsr.py
enka/enums/enum.py
enka/enums/gi.py
enka/enums/hsr.py
enka/models/enka/__init__.py
enka/models/enka/owner.py
enka/models/gi/__init__.py
enka/models/gi/build.py
enka/models/gi/character.py
enka/models/gi/costume.py
enka/models/gi/icon.py
enka/models/gi/player.py
enka/models/gi/response.py
enka/models/hsr/__init__.py
enka/models/hsr/build.py
enka/models/hsr/character.py
enka/models/hsr/icon.py
enka/models/hsr/player.py
enka/models/hsr/response.py
enka_api-2.4.4.dist-info/METADATA
enka_api-2.4.4.dist-info/WHEEL
enka_api-2.4.4.dist-info/licenses/LICENSE
enka_api-2.4.4.dist-info/RECORD
