Metadata-Version: 2.4
Name: enka-api
Version: 2.4.4
Summary: Async API wrapper for Enka Network written in Python, supports GI and HSR.
Project-URL: Homepage, https://github.com/seriaati/enka-py
Project-URL: Repository, https://github.com/seriaati/enka-py.git
Project-URL: Issues, https://github.com/seriaati/enka-py/issues
Author-email: seriaati <seria.ati@gmail.com>
License: GNU GENERAL PUBLIC LICENSE
License-File: LICENSE
Requires-Python: >=3.10
Requires-Dist: aiofiles>=24.1.0
Requires-Dist: aiohttp>=3.10.9
Requires-Dist: aiosqlite>=0.20.0
Requires-Dist: loguru>=0.7.2
Requires-Dist: orjson>=3.10.7
Requires-Dist: pydantic>=2.9.2
